{
  "method": "LOPO (Leave-One-Project-Out)",
  "pretrained_model": "gcp_results/roberta_conservative_0309_0738",
  "data": "./output/all_manually_labelled.csv",
  "augmented": true,
  "aug_d_count": 4989,
  "aug_n_count": 4995,
  "n_projects": 10,
  "n_total_samples": 1786,
  "hyperparameters": {
    "lr": 1e-05,
    "epochs": 5,
    "patience": 2,
    "batch_size": 16,
    "max_length": 512,
    "dropout": 0.1,
    "weight_decay": 0.01,
    "freeze_layers": 10
  },
  "per_project": [
    {
      "accuracy": 0.8771,
      "precision": 0.7879,
      "recall": 0.8667,
      "f1": 0.8254,
      "auc": 0.9427,
      "tp": 52,
      "tn": 105,
      "fp": 14,
      "fn": 8,
      "n": 179,
      "n_design": 60,
      "n_nondesign": 119,
      "project": "CONFSERVER"
    },
    {
      "accuracy": 0.6243,
      "precision": 0.3939,
      "recall": 0.8298,
      "f1": 0.5342,
      "auc": 0.7571,
      "tp": 39,
      "tn": 74,
      "fp": 60,
      "fn": 8,
      "n": 181,
      "n_design": 47,
      "n_nondesign": 134,
      "project": "DM"
    },
    {
      "accuracy": 0.8667,
      "precision": 0.6842,
      "recall": 0.8667,
      "f1": 0.7647,
      "auc": 0.9062,
      "tp": 39,
      "tn": 117,
      "fp": 18,
      "fn": 6,
      "n": 180,
      "n_design": 45,
      "n_nondesign": 135,
      "project": "DNN"
    },
    {
      "accuracy": 0.7079,
      "precision": 0.5,
      "recall": 0.9423,
      "f1": 0.6533,
      "auc": 0.8371,
      "tp": 49,
      "tn": 77,
      "fp": 49,
      "fn": 3,
      "n": 178,
      "n_design": 52,
      "n_nondesign": 126,
      "project": "FAB"
    },
    {
      "accuracy": 0.7322,
      "precision": 0.5161,
      "recall": 0.9231,
      "f1": 0.6621,
      "auc": 0.9328,
      "tp": 48,
      "tn": 86,
      "fp": 45,
      "fn": 4,
      "n": 183,
      "n_design": 52,
      "n_nondesign": 131,
      "project": "JRASERVER"
    },
    {
      "accuracy": 0.7797,
      "precision": 0.5952,
      "recall": 0.9091,
      "f1": 0.7194,
      "auc": 0.9101,
      "tp": 50,
      "tn": 88,
      "fp": 34,
      "fn": 5,
      "n": 177,
      "n_design": 55,
      "n_nondesign": 122,
      "project": "MESOS"
    },
    {
      "accuracy": 0.6923,
      "precision": 0.5,
      "recall": 0.8036,
      "f1": 0.6164,
      "auc": 0.7825,
      "tp": 45,
      "tn": 81,
      "fp": 45,
      "fn": 11,
      "n": 182,
      "n_design": 56,
      "n_nondesign": 126,
      "project": "MULE"
    },
    {
      "accuracy": 0.8033,
      "precision": 0.6053,
      "recall": 0.8846,
      "f1": 0.7188,
      "auc": 0.9232,
      "tp": 46,
      "tn": 101,
      "fp": 30,
      "fn": 6,
      "n": 183,
      "n_design": 52,
      "n_nondesign": 131,
      "project": "NEXUS"
    },
    {
      "accuracy": 0.6481,
      "precision": 0.3016,
      "recall": 0.5938,
      "f1": 0.4,
      "auc": 0.7272,
      "tp": 19,
      "tn": 86,
      "fp": 44,
      "fn": 13,
      "n": 162,
      "n_design": 32,
      "n_nondesign": 130,
      "project": "SERVER"
    },
    {
      "accuracy": 0.7459,
      "precision": 0.494,
      "recall": 0.9111,
      "f1": 0.6406,
      "auc": 0.8954,
      "tp": 41,
      "tn": 94,
      "fp": 42,
      "fn": 4,
      "n": 181,
      "n_design": 45,
      "n_nondesign": 136,
      "project": "TIMOB"
    }
  ],
  "mean_f1": 0.6535,
  "std_f1": 0.1143,
  "mean_auc": 0.8614,
  "std_auc": 0.0753,
  "mean_accuracy": 0.7477,
  "std_accuracy": 0.0807
}